src/__init__.py
src/main.py
src/server.py
src/services/__init__.py
src/services/client.py
src/services/config.py
src/tools/__init__.py
src/tools/karini_tools.py
karini_mcp_server_test-0.1.2.dist-info/METADATA
karini_mcp_server_test-0.1.2.dist-info/WHEEL
karini_mcp_server_test-0.1.2.dist-info/entry_points.txt
karini_mcp_server_test-0.1.2.dist-info/top_level.txt
karini_mcp_server_test-0.1.2.dist-info/RECORD
