Metadata-Version: 2.4
Name: karini-mcp-server-test
Version: 0.1.2
Summary: MCP server for Karini AI copilots, webhook recipes, dataset search, and event tracing
Author-email: Nitin Wagh <nitin.wagh@karini.ai>, Aditya Shelar <aditya.shelar@karini.ai>
Project-URL: Homepage, https://github.com/karini-ai
Project-URL: Repository, https://github.com/karini-ai/karini-mcp-server
Project-URL: Documentation, https://github.com/karini-ai/karini-mcp-server#readme
Keywords: mcp,ai,model-context-protocol,kariniai,copilot,webhook,dataset,tracing
Classifier: Programming Language :: Python :: 3.10
Classifier: Programming Language :: Python :: 3.11
Classifier: Programming Language :: Python :: 3.12
Classifier: Topic :: Software Development :: Libraries :: Python Modules
Requires-Python: >=3.10
Requires-Dist: fastmcp>=0.1.0
Requires-Dist: httpx>=0.24.0
Requires-Dist: pymongo>=4.0.0
